antchain_sdk_ak_31dc9f55b9684fe29acc7c0125a5d7a2/__init__.py
antchain_sdk_ak_31dc9f55b9684fe29acc7c0125a5d7a2/client.py
antchain_sdk_ak_31dc9f55b9684fe29acc7c0125a5d7a2/models.py
antchain_ak_31dc9f55b9684fe29acc7c0125a5d7a2-1.1.0.dist-info/LICENSE
antchain_ak_31dc9f55b9684fe29acc7c0125a5d7a2-1.1.0.dist-info/METADATA
antchain_ak_31dc9f55b9684fe29acc7c0125a5d7a2-1.1.0.dist-info/WHEEL
antchain_ak_31dc9f55b9684fe29acc7c0125a5d7a2-1.1.0.dist-info/top_level.txt
antchain_ak_31dc9f55b9684fe29acc7c0125a5d7a2-1.1.0.dist-info/RECORD
